huaweicloudsdkvod/__init__.py
huaweicloudsdkvod/v1/__init__.py
huaweicloudsdkvod/v1/vod_async_client.py
huaweicloudsdkvod/v1/vod_client.py
huaweicloudsdkvod/v1/model/__init__.py
huaweicloudsdkvod/v1/model/add_subtitle.py
huaweicloudsdkvod/v1/model/additional_manifest.py
huaweicloudsdkvod/v1/model/additional_object_process_req.py
huaweicloudsdkvod/v1/model/asset_daily_summary_result.py
huaweicloudsdkvod/v1/model/asset_details.py
huaweicloudsdkvod/v1/model/asset_info.py
huaweicloudsdkvod/v1/model/asset_process_req.py
huaweicloudsdkvod/v1/model/asset_review_req.py
huaweicloudsdkvod/v1/model/asset_summary.py
huaweicloudsdkvod/v1/model/audio_info.py
huaweicloudsdkvod/v1/model/audio_template_info.py
huaweicloudsdkvod/v1/model/base_info.py
huaweicloudsdkvod/v1/model/cancel_asset_transcode_task_request.py
huaweicloudsdkvod/v1/model/cancel_asset_transcode_task_response.py
huaweicloudsdkvod/v1/model/cancel_extract_audio_task_request.py
huaweicloudsdkvod/v1/model/cancel_extract_audio_task_response.py
huaweicloudsdkvod/v1/model/category_info.py
huaweicloudsdkvod/v1/model/cdn_log.py
huaweicloudsdkvod/v1/model/check_md5_duplication_request.py
huaweicloudsdkvod/v1/model/check_md5_duplication_response.py
huaweicloudsdkvod/v1/model/common.py
huaweicloudsdkvod/v1/model/common_info.py
huaweicloudsdkvod/v1/model/confirm_asset_upload_req.py
huaweicloudsdkvod/v1/model/confirm_asset_upload_request.py
huaweicloudsdkvod/v1/model/confirm_asset_upload_response.py
huaweicloudsdkvod/v1/model/confirm_image_upload_req.py
huaweicloudsdkvod/v1/model/confirm_image_upload_request.py
huaweicloudsdkvod/v1/model/confirm_image_upload_response.py
huaweicloudsdkvod/v1/model/cover_info.py
huaweicloudsdkvod/v1/model/create_asset_by_file_upload_req.py
huaweicloudsdkvod/v1/model/create_asset_by_file_upload_request.py
huaweicloudsdkvod/v1/model/create_asset_by_file_upload_response.py
huaweicloudsdkvod/v1/model/create_asset_category_request.py
huaweicloudsdkvod/v1/model/create_asset_category_response.py
huaweicloudsdkvod-3.1.184.dist-info/METADATA
huaweicloudsdkvod-3.1.184.dist-info/WHEEL
huaweicloudsdkvod-3.1.184.dist-info/licenses/LICENSE
huaweicloudsdkvod-3.1.184.dist-info/RECORD
